pycrud/__init__.py
pycrud/const.py
pycrud/crud/__init__.py
pycrud/crud/_core_crud.py
pycrud/crud/base_crud.py
pycrud/crud/ext/__init__.py
pycrud/crud/ext/peewee_crud.py
pycrud/crud/ext/tortoise_crud.py
pycrud/crud/query_result_row.py
pycrud/crud/sql_crud.py
pycrud/error.py
pycrud/permission.py
pycrud/pydantic_ext/__init__.py
pycrud/pydantic_ext/hex_string.py
pycrud/query.py
pycrud/types.py
pycrud/utils/__init__.py
pycrud/utils/cls_property.py
pycrud/utils/json_ex.py
pycrud/utils/name_helper.py
pycrud/values.py
pycrud-0.3.1.dist-info/LICENSE
pycrud-0.3.1.dist-info/WHEEL
pycrud-0.3.1.dist-info/METADATA
pycrud-0.3.1.dist-info/RECORD
